gitlab_recurring_issues/__init__.py
gitlab_recurring_issues/main.py
gitlab_recurring_issues-0.1.3.dist-info/entry_points.txt
gitlab_recurring_issues-0.1.3.dist-info/LICENSE.txt
gitlab_recurring_issues-0.1.3.dist-info/WHEEL
gitlab_recurring_issues-0.1.3.dist-info/METADATA
gitlab_recurring_issues-0.1.3.dist-info/RECORD
