Metadata-Version: 2.1
Name: gitlab-recurring-issues
Version: 0.1.3
Summary: Gitlab Bot to automatically (re)create recurring issues in project
License: MIT
Author: Thomas Chiroux
Author-email: thomas@chiroux.org
Requires-Python: >=3.8,<4.0
Classifier: License :: OSI Approved :: MIT License
Classifier: Programming Language :: Python :: 3
Classifier: Programming Language :: Python :: 3.8
Requires-Dist: pendulum (>=2.1.0,<3.0.0)
Requires-Dist: python-gitlab (>=2.2.0,<3.0.0)
